parides/__init__.py
parides/cli.py
parides/prom_conv.py
parides-0.6.dist-info/LICENSE
parides-0.6.dist-info/METADATA
parides-0.6.dist-info/WHEEL
parides-0.6.dist-info/entry_points.txt
parides-0.6.dist-info/top_level.txt
parides-0.6.dist-info/RECORD
