Metadata-Version: 2.1
Name: parides
Version: 0.6
Summary: Parides is a simple module to convert Prometheus metrics data to a panda dataframe or a comma-separated file.
Home-page: https://github.com/goettl79/parides
Author: Georg Öttl
Author-email: georg.oettl@gmail.com
License: Apache
Keywords: monitoring,prometheus
Platform: UNKNOWN
Classifier: Development Status :: 3 - Alpha
Classifier: Programming Language :: Python :: 3
